healer/__init__.py
healer/cli.py
healer/application/__init__.py
healer/application/healer.py
healer/application/optimizers.py
healer/application/tree_builder.py
healer/data/buildingblocks/test_100_bb.sdf
healer/data/buildingblocks/test_100_bb_processed.sdf
healer/data/reactions/datamol_rxns.json
healer/data/reactions/reactions.json
healer/domain/__init__.py
healer/domain/bb_repository.py
healer/domain/building_block.py
healer/domain/composition.py
healer/domain/enumeration_record.py
healer/domain/reaction_template.py
healer/domain/retro_step.py
healer/scripts/__init__.py
healer/scripts/preprocess_bb_source.py
healer/utils/__init__.py
healer/utils/plotting.py
healer/utils/rdkit_monkey_patch.py
healer/utils/utils.py
healer/web/__init__.py
healer/web/app.py
healer/web/celery_worker.py
healer/web/interface.py
healer/web/models.py
healer/web/routes.py
healer/web/static/favicon.ico
healer/web/static/healer_logo_no_text.png
healer/web/static/index.html
healer/web/static/assets/index-26iheSaM.js
healer/web/static/assets/index-CKoNYPy6.css
healer/web/static/ketcher/apple-touch-icon.png
healer/web/static/ketcher/apple-touch-icon.png:Zone.Identifier
healer/web/static/ketcher/asset-manifest.json
healer/web/static/ketcher/asset-manifest.json:Zone.Identifier
healer/web/static/ketcher/duo.html
healer/web/static/ketcher/duo.html:Zone.Identifier
healer/web/static/ketcher/favicon-16x16.png
healer/web/static/ketcher/favicon-16x16.png:Zone.Identifier
healer/web/static/ketcher/favicon-32x32.png
healer/web/static/ketcher/favicon-32x32.png:Zone.Identifier
healer/web/static/ketcher/favicon.ico
healer/web/static/ketcher/favicon.ico:Zone.Identifier
healer/web/static/ketcher/iframe.html
healer/web/static/ketcher/iframe.html:Zone.Identifier
healer/web/static/ketcher/index.html
healer/web/static/ketcher/index.html:Zone.Identifier
healer/web/static/ketcher/logo.svg
healer/web/static/ketcher/logo.svg:Zone.Identifier
healer/web/static/ketcher/manifest.json
mol_healer-0.1.1.dist-info/licenses/LICENSE
mol_healer-0.1.1.dist-info/METADATA
mol_healer-0.1.1.dist-info/WHEEL
mol_healer-0.1.1.dist-info/entry_points.txt
mol_healer-0.1.1.dist-info/top_level.txt
mol_healer-0.1.1.dist-info/RECORD
