Metadata-Version: 2.4
Name: mol-healer
Version: 0.1.1
Summary: Hit Expansion to Advanced Leads Using Enumerated Reactions
Author-email: Enes Kelestemur <enesk@email.unc.edu>
License-Expression: MIT
Project-URL: Homepage, https://github.com/eneskelestemur/healer
Project-URL: Repository, https://github.com/eneskelestemur/healer
Keywords: chemistry,drug-discovery,hit-expansion,enumeration,retrosynthesis
Classifier: Development Status :: 4 - Beta
Classifier: Intended Audience :: Science/Research
Classifier: Programming Language :: Python :: 3
Classifier: Programming Language :: Python :: 3.11
Classifier: Programming Language :: Python :: 3.12
Classifier: Topic :: Scientific/Engineering :: Chemistry
Requires-Python: >=3.11
License-File: LICENSE
Requires-Dist: prop-profiler>=0.2.1
Requires-Dist: numpy
Requires-Dist: pandas
Requires-Dist: tqdm
Requires-Dist: rdkit
Requires-Dist: dotenv
Provides-Extra: web
Requires-Dist: fastapi; extra == "web"
Requires-Dist: uvicorn[standard]; extra == "web"
Requires-Dist: celery[redis]; extra == "web"
Provides-Extra: dev
Requires-Dist: pytest; extra == "dev"
Dynamic: license-file
